whisper_run/__init__.py
whisper_run/__main__.py
whisper_run/arg_parser.py
whisper_run/audio_converter.py
whisper_run/audio_processor.py
whisper_run/cli.py
whisper_run/config.py
whisper_run/diarization_pipeline.py
whisper_run/inference_session.py
whisper_run/main.py
whisper_run/pyannote_onnx.py
whisper_run/segmentation-3.0.onnx
whisper_run/transcription_pipeline.py
whisper_run/utils.py
whisper_run-1.3.0.dist-info/LICENSE
whisper_run-1.3.0.dist-info/METADATA
whisper_run-1.3.0.dist-info/WHEEL
whisper_run-1.3.0.dist-info/entry_points.txt
whisper_run-1.3.0.dist-info/top_level.txt
whisper_run-1.3.0.dist-info/RECORD
