Metadata-Version: 2.1
Name: whisper-run
Version: 1.3.0
Summary: Whisper with speaker diarization
Home-page: https://github.com/gorkemkaramolla/whisper-run
Author: Görkem Karamolla
Author-email: gorkemkaramolla@gmail.com
Classifier: Programming Language :: Python :: 3
Classifier: License :: OSI Approved :: MIT License
Classifier: Operating System :: OS Independent
Requires-Python: >=3.8
License-File: LICENSE
Requires-Dist: numpy >=1
Requires-Dist: pydub >=0.24.1
Requires-Dist: torchvision >=0.17.0
Requires-Dist: inquirer >=3.2.0
Requires-Dist: faster-whisper >=1.0.0
Requires-Dist: torch >=2.1.0
Requires-Dist: librosa ==0.10.2.post1
Requires-Dist: tqdm ==4.66.4
Requires-Dist: orjson ==3.10.6
